setup.py
cytokit/__init__.py
cytokit/config.py
cytokit/data.py
cytokit/io.py
cytokit/io_test.py
cytokit/math.py
cytokit/simulation.py
cytokit/tiling.py
cytokit.egg-info/PKG-INFO
cytokit.egg-info/SOURCES.txt
cytokit.egg-info/dependency_links.txt
cytokit.egg-info/entry_points.txt
cytokit.egg-info/requires.txt
cytokit.egg-info/top_level.txt
cytokit/cli/__init__.py
cytokit/cli/analysis.py
cytokit/cli/application.py
cytokit/cli/config.py
cytokit/cli/download.py
cytokit/cli/main.py
cytokit/cli/operator.py
cytokit/cli/processor.py
cytokit/cytometry/__init__.py
cytokit/cytometry/cytometer.py
cytokit/cytometry/data.py
cytokit/cytometry/models/__init__.py
cytokit/cytometry/models/unet_v1.py
cytokit/cytometry/models/unet_v2.py
cytokit/exec/__init__.py
cytokit/exec/pipeline.py
cytokit/function/__init__.py
cytokit/function/core.py
cytokit/function/data.py
cytokit/image/__init__.py
cytokit/image/color.py
cytokit/image/ops.py
cytokit/image/proc.py
cytokit/image/visualize.py
cytokit/miq/__init__.py
cytokit/miq/constants.py
cytokit/miq/evaluation.py
cytokit/miq/miq.py
cytokit/miq/prediction.py
cytokit/misc/__init__.py
cytokit/misc/montage.py
cytokit/ops/__init__.py
cytokit/ops/best_focus.py
cytokit/ops/cytometry.py
cytokit/ops/deconvolution.py
cytokit/ops/drift_compensation.py
cytokit/ops/illumination_correction.py
cytokit/ops/op.py
cytokit/ops/spectral_unmixing.py
cytokit/ops/tile_crop.py
cytokit/ops/tile_generator.py
cytokit/ops/tile_summary.py
cytokit/utils/__init__.py
cytokit/utils/ij_utils.py
cytokit/utils/np_utils.py
cytokit/utils/tf_utils.py
tests/cli/__init__.py
tests/cli/config_cli_test.py
tests/ops/__init__.py
tests/ops/drift_compensation_test.py