Metadata-Version: 1.1
Name: cytokit
Version: 0.0.1
Summary: Microscopy Image Cytometry Toolkit
Home-page: UNKNOWN
Author: Eric Czech
Author-email: eric@hammerlab.org
License: http://www.apache.org/licenses/LICENSE-2.0.html
Platform: UNKNOWN
Classifier: Environment :: Console
Classifier: Operating System :: OS Independent
Classifier: Intended Audience :: Science/Research
Classifier: Topic :: Scientific/Engineering :: Bio-Informatics
Classifier: License :: OSI Approved :: Apache Software License
Classifier: Programming Language :: Python :: 3.6
